{
    "asset": {
        "format": "PNG",
        "id": "37550c946f4401206b100eea6deb00e0",
        "name": "IMG_3018.PNG",
        "path": "file:C:/Users/stitc/OneDrive/%E3%83%87%E3%82%B9%E3%82%AF%E3%83%88%E3%83%83%E3%83%97/%E6%95%99%E7%A4%BA%E3%83%87%E3%83%BC%E3%82%BF/Image/IMG_3018.PNG",
        "size": {
            "width": 2224,
            "height": 1668
        },
        "state": 2,
        "type": 1
    },
    "regions": [
        {
            "id": "FBKHUHcvY",
            "type": "RECTANGLE",
            "tags": [
                "R"
            ],
            "boundingBox": {
                "height": 122.75324675324676,
                "width": 92.06493506493507,
                "left": 1501.0194805194806,
                "top": 209.4025974025974
            },
            "points": [
                {
                    "x": 1501.0194805194806,
                    "y": 209.4025974025974
                },
                {
                    "x": 1593.0844155844156,
                    "y": 209.4025974025974
                },
                {
                    "x": 1593.0844155844156,
                    "y": 332.1558441558442
                },
                {
                    "x": 1501.0194805194806,
                    "y": 332.1558441558442
                }
            ]
        },
        {
            "id": "xtFe-i0RX",
            "type": "RECTANGLE",
            "tags": [
                "E"
            ],
            "boundingBox": {
                "height": 115.53246753246754,
                "width": 106.50649350649351,
                "left": 1598.5,
                "top": 211.2077922077922
            },
            "points": [
                {
                    "x": 1598.5,
                    "y": 211.2077922077922
                },
                {
                    "x": 1705.0064935064936,
                    "y": 211.2077922077922
                },
                {
                    "x": 1705.0064935064936,
                    "y": 326.7402597402598
                },
                {
                    "x": 1598.5,
                    "y": 326.7402597402598
                }
            ]
        },
        {
            "id": "enwhgyhjm",
            "type": "RECTANGLE",
            "tags": [
                "N"
            ],
            "boundingBox": {
                "height": 106.50649350649351,
                "width": 93.87012987012987,
                "left": 1712.2272727272727,
                "top": 214.8181818181818
            },
            "points": [
                {
                    "x": 1712.2272727272727,
                    "y": 214.8181818181818
                },
                {
                    "x": 1806.0974025974026,
                    "y": 214.8181818181818
                },
                {
                    "x": 1806.0974025974026,
                    "y": 321.32467532467535
                },
                {
                    "x": 1712.2272727272727,
                    "y": 321.32467532467535
                }
            ]
        },
        {
            "id": "qnwpY3x3N",
            "type": "RECTANGLE",
            "tags": [
                "A"
            ],
            "boundingBox": {
                "height": 120.94805194805195,
                "width": 122.75324675324676,
                "left": 1802.487012987013,
                "top": 205.7922077922078
            },
            "points": [
                {
                    "x": 1802.487012987013,
                    "y": 205.7922077922078
                },
                {
                    "x": 1925.2402597402597,
                    "y": 205.7922077922078
                },
                {
                    "x": 1925.2402597402597,
                    "y": 326.7402597402598
                },
                {
                    "x": 1802.487012987013,
                    "y": 326.7402597402598
                }
            ]
        },
        {
            "id": "ospLHsbxi",
            "type": "RECTANGLE",
            "tags": [
                "T"
            ],
            "boundingBox": {
                "height": 124.55844155844156,
                "width": 90.25974025974025,
                "left": 1925.2402597402597,
                "top": 203.987012987013
            },
            "points": [
                {
                    "x": 1925.2402597402597,
                    "y": 203.987012987013
                },
                {
                    "x": 2015.5,
                    "y": 203.987012987013
                },
                {
                    "x": 2015.5,
                    "y": 328.54545454545456
                },
                {
                    "x": 1925.2402597402597,
                    "y": 328.54545454545456
                }
            ]
        },
        {
            "id": "AtxhBW3uO",
            "type": "RECTANGLE",
            "tags": [
                "A"
            ],
            "boundingBox": {
                "height": 122.75324675324676,
                "width": 117.33766233766234,
                "left": 2017.3051948051948,
                "top": 203.987012987013
            },
            "points": [
                {
                    "x": 2017.3051948051948,
                    "y": 203.987012987013
                },
                {
                    "x": 2134.6428571428573,
                    "y": 203.987012987013
                },
                {
                    "x": 2134.6428571428573,
                    "y": 326.7402597402598
                },
                {
                    "x": 2017.3051948051948,
                    "y": 326.7402597402598
                }
            ]
        }
    ],
    "version": "2.1.0"
}