{
    "asset": {
        "format": "PNG",
        "id": "73e7f7d7b9c4fb17760d2b4aa3217921",
        "name": "IMG_2975.PNG",
        "path": "file:C:/Users/stitc/OneDrive/%E3%83%87%E3%82%B9%E3%82%AF%E3%83%88%E3%83%83%E3%83%97/%E6%95%99%E7%A4%BA%E3%83%87%E3%83%BC%E3%82%BF/Image/IMG_2975.PNG",
        "size": {
            "width": 2224,
            "height": 1668
        },
        "state": 2,
        "type": 1
    },
    "regions": [
        {
            "id": "ZiP40b2eE",
            "type": "RECTANGLE",
            "tags": [
                "C"
            ],
            "boundingBox": {
                "height": 99.28571428571429,
                "width": 129.97402597402598,
                "left": 1668.9025974025974,
                "top": 223.84415584415586
            },
            "points": [
                {
                    "x": 1668.9025974025974,
                    "y": 223.84415584415586
                },
                {
                    "x": 1798.8766233766235,
                    "y": 223.84415584415586
                },
                {
                    "x": 1798.8766233766235,
                    "y": 323.12987012987014
                },
                {
                    "x": 1668.9025974025974,
                    "y": 323.12987012987014
                }
            ]
        },
        {
            "id": "OJjkJMbBL",
            "type": "RECTANGLE",
            "tags": [
                "O"
            ],
            "boundingBox": {
                "height": 140.80519480519482,
                "width": 92.06493506493507,
                "left": 1795.2662337662339,
                "top": 203.987012987013
            },
            "points": [
                {
                    "x": 1795.2662337662339,
                    "y": 203.987012987013
                },
                {
                    "x": 1887.331168831169,
                    "y": 203.987012987013
                },
                {
                    "x": 1887.331168831169,
                    "y": 344.7922077922078
                },
                {
                    "x": 1795.2662337662339,
                    "y": 344.7922077922078
                }
            ]
        },
        {
            "id": "LFJMWPRoP",
            "type": "RECTANGLE",
            "tags": [
                "C"
            ],
            "boundingBox": {
                "height": 110.11688311688312,
                "width": 129.97402597402598,
                "left": 1881.9155844155844,
                "top": 220.23376623376623
            },
            "points": [
                {
                    "x": 1881.9155844155844,
                    "y": 220.23376623376623
                },
                {
                    "x": 2011.8896103896104,
                    "y": 220.23376623376623
                },
                {
                    "x": 2011.8896103896104,
                    "y": 330.35064935064935
                },
                {
                    "x": 1881.9155844155844,
                    "y": 330.35064935064935
                }
            ]
        },
        {
            "id": "rLJKYQnpZ",
            "type": "RECTANGLE",
            "tags": [
                "O"
            ],
            "boundingBox": {
                "height": 137.1948051948052,
                "width": 93.87012987012987,
                "left": 2008.2792207792209,
                "top": 207.5974025974026
            },
            "points": [
                {
                    "x": 2008.2792207792209,
                    "y": 207.5974025974026
                },
                {
                    "x": 2102.1493506493507,
                    "y": 207.5974025974026
                },
                {
                    "x": 2102.1493506493507,
                    "y": 344.7922077922078
                },
                {
                    "x": 2008.2792207792209,
                    "y": 344.7922077922078
                }
            ]
        }
    ],
    "version": "2.1.0"
}